pynodered/__init__.py
pynodered/core.py
pynodered/server.py
pynodered/ttldict.py
pynodered/imported_modules/__init__.py
pynodered/templates/httprequest.html.in
pynodered/templates/httprequest.js.in
pynodered-0.1.0.dist-info/AUTHORS.rst
pynodered-0.1.0.dist-info/LICENSE
pynodered-0.1.0.dist-info/METADATA
pynodered-0.1.0.dist-info/WHEEL
pynodered-0.1.0.dist-info/entry_points.txt
pynodered-0.1.0.dist-info/top_level.txt
pynodered-0.1.0.dist-info/RECORD
