Metadata-Version: 2.1
Name: pynodered
Version: 0.1.0
Summary: make python function easily accessible from Node-RED 
Home-page: https://github.com/ghislainp/pynodered
Author: Ghislain Picard
Author-email: ghislain.picard@univ-grenoble-alpes.fr
License: GNU General Public License v3
Keywords: pynodered
Platform: UNKNOWN
Classifier: Development Status :: 2 - Pre-Alpha
Classifier: Intended Audience :: Developers
Classifier: License :: OSI Approved :: GNU General Public License v3 (GPLv3)
Classifier: Natural Language :: English
Classifier: Programming Language :: Python :: 3
Classifier: Programming Language :: Python :: 3.5
Classifier: Programming Language :: Python :: 3.6
Classifier: Programming Language :: Python :: 3.7
Requires-Dist: flask
Requires-Dist: json-rpc
